quickbase_json/__init__.py
quickbase_json/auth.py
quickbase_json/client.py
quickbase_json/conftest.py
quickbase_json/helpers.py
quickbase_json/qb_insert_update_response.py
quickbase_json/qb_linked_record.py
quickbase_json/qb_response.py
quickbase_json/wiki.py
quickbase_json/xml_stuff.py
quickbase_json_api_client-0.3.0.dist-info/LICENSE
quickbase_json_api_client-0.3.0.dist-info/METADATA
quickbase_json_api_client-0.3.0.dist-info/WHEEL
quickbase_json_api_client-0.3.0.dist-info/top_level.txt
quickbase_json_api_client-0.3.0.dist-info/RECORD
