Metadata-Version: 2.1
Name: quickbase-json-api-client
Version: 0.3.0
Summary: Python wrapper for quickbase JSON API.
Home-page: https://github.com/robswc/quickbase-json-api-client
Author: Robert Carroll
Author-email: rob@shenandoah.capital
Project-URL: Bug Tracker, https://github.com/robswc/quickbase-json-api-client/issues
Classifier: Programming Language :: Python :: 3
Classifier: License :: OSI Approved :: MIT License
Classifier: Operating System :: OS Independent
Requires-Python: >=3.6
License-File: LICENSE
